{
  "name": "Franklin Henry",
  "age": 49,
  "address": {
    "street": "Gowo Avenue",
    "city": "Tarulav",
    "state": "TX",
    "zip": "03625"
  },
  "contact": {
    "phone": "(621) 308-7890",
    "servicePhone": "800938174"
  },
  "birthday": "1962-05-31T08:27:37.258Z",
  "ip": "254.203.88.61",
  "foo": "bar",
  "profile": {
    "about": "Lazhaep coikhi iru dipdub ben ri bo ufeda betopnet ojumogeg horko meterduj so ovtisit pu. Go elidewum uhozef ne kupru giicubim fap zumme vuc gookauw bezo fedva ew. Is wi cal jufiddul abuwaj uhadgoz esoagoib ubaoku ravo bud hinlag gehradora rukuvata am. Ecumej fepop zugpaenu cu jir belaje irva li baojakef nun gip sisodo uze nadwupwu ol mevri gen him. Rap uhtitjun kibesa tiar epew dovwazawo hounobum uznih du bizwu sanufuipu vatgu ijetocji fup dumumej ziwcavotu zawme.",
    "bio": "Ba cirboh dukehfa mik venwe uwhorlig nece ba hibjahkal ajo imeiv douliruz bih difiazo huwzopec zocjaz od vapbuar. Bowtifduj hu wosow va du sube weefnez wi muve bowopos ifuceuc pijrow. Ge ebpov warneceka we dickaffi tofwialu lilu ofwivnor ina jofkotit fedwuk cobpar. Asumop ecum kozzoodo rucjepsof jidel rihivo jed ve irogo rejlozu cilzitnet ni boavahaf. Poaptuz hej vic evbu gabuzu uhane cebvohsi bok erzegham kazuw wohwas dur paup."
  },
  "apiKey": "e55dccc9d8e7c0eec2e1ae3262a4d12bae569a4a03a2be69991d08a496dd7cd6",
  "currency": {
    "code": "SCR",
    "name": "Seychelles Rupee"
  }
}