{
  "name": "Amelia Brock",
  "age": 26,
  "address": {
    "street": "Radi Pass",
    "city": "Iragugiw",
    "state": "OR",
    "zip": "53686"
  },
  "contact": {
    "phone": "(342) 855-4750",
    "servicePhone": "800863615"
  },
  "birthday": "1995-09-07T20:58:20.727Z",
  "ip": "39.100.227.70",
  "foo": "bar",
  "profile": {
    "about": "Loteg jicojkig um to laolo tesvaeho ud emo jopgem hulwi oweedo ekele adrub batioc sagog ziveh takaw vogma. Pobbafe ulegi lolug meri ka icifaj updivi awasi zudah kihdupzof va womu vapgedna cuhevpa hooge. Doshacara je sibogez lurew hasikne hon vacvelin ji hu alge wenifi rep.",
    "bio": "Wanpog iz ovcak ijoti iviboome huvkevik endew hujgij vuce wewbe giacovur mig ubemuw. Zoc bec sukcun mirpif dufelol zo balrihi guzza za umetufnah raw ih urepemlu bigdim. Ikola tefkah evoguce ruomada wunce cubbi fut ocur pokwap rine jozjufi sured sib ro akemo aca zehraj. Dad li ugeca obe su hetwetop gometijet lepoh cimup nug pu wi namlinfi alagav ga wiczulrol noppuv. Rowuhwih ja sibakaha riucavu mi doede catfa ihlavej joise ifcubo efilevos jifpuwem bun uki waupeepo."
  },
  "apiKey": "6e86390e42a1bea90ccdcd8306032b92e1f47abb09ebf8cb41d654d6171f3071",
  "currency": {
    "code": "BRL",
    "name": "Brazil Real"
  }
}